[{"number":1,"team":"Lens","matches":8,"wins":7,"draws":0,"loses":1,"goals":16,"ga":4,"points":21,"xG":21.32,"NPxG":19.04,"xGA":8.94,"NPxGA":8.18,"NPxGD":10.86,"ppda":13.17,"ppda_allowed":12.25,"deep":70,"deep_allowed":48,"xPTS":18.96},{"number":2,"team":"Marseille","matches":8,"wins":6,"draws":2,"loses":0,"goals":24,"ga":8,"points":20,"xG":20.48,"NPxG":16.68,"xGA":7.25,"NPxGA":7.25,"NPxGD":9.43,"ppda":9.89,"ppda_allowed":23.48,"deep":76,"deep_allowed":31,"xPTS":18.56},{"number":3,"team":"Paris Saint Germain","matches":7,"wins":6,"draws":1,"loses":0,"goals":17,"ga":3,"points":19,"xG":16.45,"NPxG":14.93,"xGA":5.88,"NPxGA":5.88,"NPxGD":9.05,"ppda":6.17,"ppda_allowed":22.87,"deep":100,"deep_allowed":23,"xPTS":16.44},{"number":4,"team":"Lille","matches":8,"wins":6,"draws":1,"loses":1,"goals":16,"ga":6,"points":19,"xG":17.91,"NPxG":14.87,"xGA":8.73,"NPxGA":8.73,"NPxGD":6.14,"ppda":10.42,"ppda_allowed":13.23,"deep":89,"deep_allowed":31,"xPTS":16.23},{"number":5,"team":"Lyon","matches":8,"wins":6,"draws":0,"loses":2,"goals":14,"ga":6,"points":18,"xG":16.15,"NPxG":15.39,"xGA":7.77,"NPxGA":6.89,"NPxGD":8.49,"ppda":10.59,"ppda_allowed":14.94,"deep":55,"deep_allowed":25,"xPTS":16.68},{"number":6,"team":"Rennes","matches":8,"wins":5,"draws":2,"loses":1,"goals":18,"ga":8,"points":17,"xG":16.3,"NPxG":15.54,"xGA":12.45,"NPxGA":11.69,"NPxGD":3.85,"ppda":11.15,"ppda_allowed":9.78,"deep":37,"deep_allowed":46,"xPTS":13.74},{"number":7,"team":"Strasbourg","matches":8,"wins":5,"draws":1,"loses":2,"goals":14,"ga":4,"points":16,"xG":15.56,"NPxG":14.8,"xGA":5.84,"NPxGA":5.08,"NPxGD":9.72,"ppda":11.25,"ppda_allowed":15.16,"deep":49,"deep_allowed":27,"xPTS":16.24},{"number":8,"team":"Monaco","matches":9,"wins":5,"draws":1,"loses":3,"goals":17,"ga":15,"points":16,"xG":18.23,"NPxG":15.05,"xGA":13.68,"NPxGA":11.4,"NPxGD":3.65,"ppda":8.39,"ppda_allowed":11.84,"deep":84,"deep_allowed":71,"xPTS":15},{"number":9,"team":"Lorient","matches":8,"wins":4,"draws":3,"loses":1,"goals":17,"ga":14,"points":15,"xG":15.73,"NPxG":14.06,"xGA":10.48,"NPxGA":8.2,"NPxGD":5.85,"ppda":19.95,"ppda_allowed":8.25,"deep":59,"deep_allowed":47,"xPTS":13.89},{"number":10,"team":"Angers","matches":8,"wins":4,"draws":2,"loses":2,"goals":12,"ga":7,"points":14,"xG":11.1,"NPxG":10.34,"xGA":10.26,"NPxGA":8.74,"NPxGD":1.6,"ppda":15.05,"ppda_allowed":10.47,"deep":32,"deep_allowed":44,"xPTS":10.92},{"number":11,"team":"Nice","matches":9,"wins":4,"draws":2,"loses":3,"goals":12,"ga":12,"points":14,"xG":15.38,"NPxG":14.62,"xGA":14.46,"NPxGA":12.18,"NPxGD":2.44,"ppda":14.75,"ppda_allowed":11.69,"deep":51,"deep_allowed":69,"xPTS":13.58},{"number":12,"team":"Brest","matches":8,"wins":3,"draws":3,"loses":2,"goals":12,"ga":11,"points":12,"xG":15.66,"NPxG":12.62,"xGA":11.03,"NPxGA":11.03,"NPxGD":1.59,"ppda":10.68,"ppda_allowed":13.13,"deep":40,"deep_allowed":53,"xPTS":14.57},{"number":13,"team":"Toulouse","matches":9,"wins":3,"draws":3,"loses":3,"goals":14,"ga":14,"points":12,"xG":14.03,"NPxG":10.99,"xGA":10.62,"NPxGA":9.1,"NPxGD":1.89,"ppda":13.93,"ppda_allowed":9.11,"deep":51,"deep_allowed":47,"xPTS":15.22},{"number":14,"team":"Le Havre","matches":8,"wins":2,"draws":4,"loses":2,"goals":9,"ga":8,"points":10,"xG":12.35,"NPxG":10.07,"xGA":7.82,"NPxGA":7.06,"NPxGD":3.02,"ppda":10.23,"ppda_allowed":12.41,"deep":34,"deep_allowed":30,"xPTS":14.68},{"number":15,"team":"Auxerre","matches":9,"wins":3,"draws":1,"loses":5,"goals":10,"ga":11,"points":10,"xG":12.46,"NPxG":9.42,"xGA":10.03,"NPxGA":9.27,"NPxGD":0.15,"ppda":13.09,"ppda_allowed":8.03,"deep":40,"deep_allowed":51,"xPTS":14.04},{"number":16,"team":"Paris FC","matches":8,"wins":2,"draws":2,"loses":4,"goals":12,"ga":15,"points":8,"xG":13.07,"NPxG":11.55,"xGA":11.64,"NPxGA":10.88,"NPxGD":0.68,"ppda":11.44,"ppda_allowed":18.31,"deep":62,"deep_allowed":26,"xPTS":11.72},{"number":17,"team":"Metz","matches":8,"wins":2,"draws":2,"loses":4,"goals":7,"ga":10,"points":8,"xG":8.63,"NPxG":6.35,"xGA":10.74,"NPxGA":9.98,"NPxGD":-3.63,"ppda":17.18,"ppda_allowed":11.32,"deep":19,"deep_allowed":67,"xPTS":9.55},{"number":18,"team":"Nantes","matches":8,"wins":1,"draws":2,"loses":5,"goals":8,"ga":15,"points":5,"xG":9.27,"NPxG":7.6,"xGA":15.75,"NPxGA":14.99,"NPxGD":-7.39,"ppda":13.99,"ppda_allowed":9.71,"deep":32,"deep_allowed":64,"xPTS":7.16}]